prediction_metrics_backtesting.py
prediction_metrics_backtester-0.1.0.dist-info/licenses/LICENSE
prediction_metrics_backtester-0.1.0.dist-info/METADATA
prediction_metrics_backtester-0.1.0.dist-info/WHEEL
prediction_metrics_backtester-0.1.0.dist-info/entry_points.txt
prediction_metrics_backtester-0.1.0.dist-info/top_level.txt
prediction_metrics_backtester-0.1.0.dist-info/RECORD
