Metadata-Version: 2.4
Name: prediction-metrics-backtester
Version: 0.1.0
Summary: A flexible backtesting framework for evaluating trading strategies based on prediction metrics
Home-page: https://github.com/nawihu/prediction-metrics-backtester
Author: Nathaniel William Huff
Author-email: nathanielwilliam117@gmail.com
Project-URL: Bug Reports, https://github.com/nawihu/prediction-metrics-backtester/issues
Project-URL: Source, https://github.com/nawihu/prediction-metrics-backtester
Project-URL: Documentation, https://github.com/nawihu/prediction-metrics-backtester/wiki
Keywords: backtesting trading finance prediction metrics strategy
Classifier: Development Status :: 4 - Beta
Classifier: Intended Audience :: Financial and Insurance Industry
Classifier: Topic :: Office/Business :: Financial :: Investment
Classifier: License :: OSI Approved :: MIT License
Classifier: Operating System :: OS Independent
Classifier: Programming Language :: Python :: 3
Classifier: Programming Language :: Python :: 3.7
Classifier: Programming Language :: Python :: 3.8
Classifier: Programming Language :: Python :: 3.9
Classifier: Programming Language :: Python :: 3.10
Classifier: Programming Language :: Python :: 3.11
Classifier: Programming Language :: Python :: 3.12
Requires-Python: >=3.7
License-File: LICENSE
Requires-Dist: pandas>=1.3.0
Requires-Dist: numpy>=1.20.0
Requires-Dist: matplotlib>=3.4.0
Requires-Dist: seaborn>=0.11.0
Dynamic: author
Dynamic: author-email
Dynamic: classifier
Dynamic: description
Dynamic: description-content-type
Dynamic: home-page
Dynamic: keywords
Dynamic: license-file
Dynamic: project-url
Dynamic: requires-dist
Dynamic: requires-python
Dynamic: summary
